geyserworx_api/__init__.py
geyserworx_api/geyserworx_api.py
geyserworx_api-1.0.3.dist-info/METADATA
geyserworx_api-1.0.3.dist-info/WHEEL
geyserworx_api-1.0.3.dist-info/licenses/LICENSE
geyserworx_api-1.0.3.dist-info/RECORD
